nemoa/__init__.py
nemoa/typing.py
nemoa/base/__init__.py
nemoa/base/array.py
nemoa/base/nbase.py
nemoa/core/__init__.py
nemoa/core/cli.py
nemoa/core/dcmeta.py
nemoa/core/log.py
nemoa/core/session.py
nemoa/core/tty.py
nemoa/core/ws.py
nemoa/core/ui/__init__.py
nemoa/core/ui/shell.py
nemoa/data/testsuite.zip
nemoa/data/tutorial.zip
nemoa/dataset/__init__.py
nemoa/dataset/builder/__init__.py
nemoa/dataset/builder/plain.py
nemoa/dataset/classes/__init__.py
nemoa/dataset/classes/base.py
nemoa/dataset/commons/__init__.py
nemoa/dataset/commons/labels/__init__.py
nemoa/dataset/commons/labels/gene.py
nemoa/dataset/exports/__init__.py
nemoa/dataset/exports/archive.py
nemoa/dataset/exports/image.py
nemoa/dataset/exports/text.py
nemoa/dataset/imports/__init__.py
nemoa/dataset/imports/archive.py
nemoa/dataset/imports/text.py
nemoa/math/__init__.py
nemoa/math/curve.py
nemoa/math/graph.py
nemoa/math/matrix.py
nemoa/math/regress.py
nemoa/math/stat.py
nemoa/math/test.py
nemoa/math/vector.py
nemoa/model/__init__.py
nemoa/model/analysis/__init__.py
nemoa/model/analysis/__test__.py
nemoa/model/analysis/bayes.py
nemoa/model/analysis/generic.py
nemoa/model/analysis/hybrid.py
nemoa/model/analysis/markov.py
nemoa/model/builder/__init__.py
nemoa/model/builder/base.py
nemoa/model/classes/__init__.py
nemoa/model/classes/base.py
nemoa/model/evaluation/__init__.py
nemoa/model/evaluation/ann.py
nemoa/model/evaluation/base.py
nemoa/model/evaluation/dbn.py
nemoa/model/evaluation/rbm.py
nemoa/model/exports/__init__.py
nemoa/model/exports/archive.py
nemoa/model/exports/image.py
nemoa/model/imports/__init__.py
nemoa/model/imports/archive.py
nemoa/model/morphisms/__init__.py
nemoa/model/morphisms/ann.py
nemoa/model/morphisms/base.py
nemoa/model/morphisms/dbn.py
nemoa/model/morphisms/rbm.py
nemoa/network/__init__.py
nemoa/network/builder/__init__.py
nemoa/network/builder/layer.py
nemoa/network/classes/__init__.py
nemoa/network/classes/base.py
nemoa/network/classes/layer.py
nemoa-0.5.582.dist-info/LICENSE
nemoa-0.5.582.dist-info/METADATA
nemoa-0.5.582.dist-info/WHEEL
nemoa-0.5.582.dist-info/entry_points.txt
nemoa-0.5.582.dist-info/top_level.txt
nemoa-0.5.582.dist-info/RECORD
